setup.cfg
setup.py
watch/__init__.py
watch/builtins.py
watch/core.py
watch.egg-info/PKG-INFO
watch.egg-info/SOURCES.txt
watch.egg-info/dependency_links.txt
watch.egg-info/not-zip-safe
watch.egg-info/top_level.txt