Metadata-Version: 1.1
Name: watch
Version: 0.2.6
Summary: A stupid monadic fields tracker.
Home-page: https://github.com/magniff/watch
Author: magniff
Author-email: UNKNOWN
License: MIT license
Platform: unix
Platform: linux
Platform: osx
Platform: win32
Classifier: Programming Language :: Python :: 3.1
Classifier: Programming Language :: Python :: 3.2
Classifier: Programming Language :: Python :: 3.3
Classifier: Programming Language :: Python :: 3.4
Classifier: Programming Language :: Python :: 3.5
Classifier: Programming Language :: Python :: 3.6
Classifier: Programming Language :: Python :: 3.7
